{
    "365109865347153921" : {
        "295776945810046976" : [
            "SerMar"
        ],
        "310184535381770240" : [
            "NotHereExpectTDeath",
            "NotHereExpectDeath",
            "[Insert Will to Live Here]",
            "Cherry Monster"
        ],
        "394059160045486100" : [
            "\ud83c\udf7c\u00c7ryb\u00e5by\ud83c\udf7c"
        ]
    },
    "394233253562810379" : {
        "348668263862894593" : [
            ".ponut"
        ],
        "426527685536251914" : [
            "savage bot"
        ]
    }
}